odoo/addons/hr_shift_holidays_public/README.rst
odoo/addons/hr_shift_holidays_public/__init__.py
odoo/addons/hr_shift_holidays_public/__manifest__.py
odoo/addons/hr_shift_holidays_public/i18n/hr_shift_holidays_public.pot
odoo/addons/hr_shift_holidays_public/i18n/it.po
odoo/addons/hr_shift_holidays_public/models/__init__.py
odoo/addons/hr_shift_holidays_public/models/shift_planning_line.py
odoo/addons/hr_shift_holidays_public/readme/CONTRIBUTORS.md
odoo/addons/hr_shift_holidays_public/readme/DESCRIPTION.md
odoo/addons/hr_shift_holidays_public/readme/USAGE.md
odoo/addons/hr_shift_holidays_public/static/description/icon.png
odoo/addons/hr_shift_holidays_public/static/description/index.html
odoo/addons/hr_shift_holidays_public/static/description/public_holidays.png
odoo14_addon_hr_shift_holidays_public-14.0.1.0.1.dev5.dist-info/METADATA
odoo14_addon_hr_shift_holidays_public-14.0.1.0.1.dev5.dist-info/WHEEL
odoo14_addon_hr_shift_holidays_public-14.0.1.0.1.dev5.dist-info/top_level.txt
odoo14_addon_hr_shift_holidays_public-14.0.1.0.1.dev5.dist-info/RECORD
