Metadata-Version: 2.1
Name: odoo14-addon-hr_shift_holidays_public
Version: 14.0.1.0.1.dev5
Summary: Avoid planning shifts on holidays
Home-page: https://github.com/OCA/shift-planning
Author: Tecnativa, Odoo Community Association (OCA)
Author-email: support@odoo-community.org
License: AGPL-3
Classifier: Programming Language :: Python
Classifier: Framework :: Odoo
Classifier: Framework :: Odoo :: 14.0
Classifier: License :: OSI Approved :: GNU Affero General Public License v3
Requires-Python: >=3.6
Requires-Dist: odoo14-addon-hr-holidays-public
Requires-Dist: odoo14-addon-hr-shift
Requires-Dist: odoo<14.1dev,>=14.0a
